AUTHORS.rst
CONTRIBUTING.rst
HISTORY.rst
LICENSE
MANIFEST.in
README.rst
setup.cfg
setup.py
licenraptor/__init__.py
licenraptor/__main__.py
licenraptor/base.py
licenraptor/core.py
licenraptor/licenraptor.py
licenraptor/licenses.py
licenraptor.egg-info/PKG-INFO
licenraptor.egg-info/SOURCES.txt
licenraptor.egg-info/dependency_links.txt
licenraptor.egg-info/entry_points.txt
licenraptor.egg-info/not-zip-safe
licenraptor.egg-info/requires.txt
licenraptor.egg-info/top_level.txt
licenraptor/templates/AGPL-3.0
licenraptor/templates/AGPL-3.0+
licenraptor/templates/AGPL-3.0+__header
licenraptor/templates/AGPL-3.0__header
licenraptor/templates/Apache-1.0
licenraptor/templates/Apache-1.1
licenraptor/templates/Apache-2.0
licenraptor/templates/Apache-2.0__header
licenraptor/templates/BSD-2-Clause
licenraptor/templates/BSD-3-Clause
licenraptor/templates/GPL-2.0
licenraptor/templates/GPL-2.0+
licenraptor/templates/GPL-2.0+__header
licenraptor/templates/GPL-2.0__header
licenraptor/templates/GPL-3.0
licenraptor/templates/GPL-3.0+
licenraptor/templates/GPL-3.0+__header
licenraptor/templates/GPL-3.0__header
licenraptor/templates/LGPL-2.1
licenraptor/templates/LGPL-2.1+
licenraptor/templates/LGPL-2.1+__header
licenraptor/templates/LGPL-2.1__header
licenraptor/templates/LGPL-3.0
licenraptor/templates/LGPL-3.0+
licenraptor/templates/LGPL-3.0+__header
licenraptor/templates/LGPL-3.0__header
licenraptor/templates/MIT
tests/__init__.py
tests/test_base.py
tests/test_db.py
tests/test_licenraptor.py
tests/test_render.py
tests/files/CUSTOM